<experiment>
  <configHash>15bf76602b098f2963ae24bfe3d94065</configHash>
  <outputDir>/home/pi/external_hdd/pi/android-runner/examples/monsoon/final/output/2021.07.27_215824/</outputDir>
  <runsToRun>
    </runsToRun>
  <runsDone>
    <run runId="196">
      <device>nexus5x</device>
      <path>berlinomagazine.com/noremovepreload</path>
      <browser>chrome</browser>
      <runCount>2</runCount>
    </run>
    <run runId="231">
      <device>nexus5x</device>
      <path>beegru.com/removepreload</path>
      <browser>chrome</browser>
      <runCount>2</runCount>
    </run>
    <run runId="156">
      <device>nexus5x</device>
      <path>dji.com/noremovepreload</path>
      <browser>chrome</browser>
      <runCount>2</runCount>
    </run>
    <run runId="303">
      <device>nexus5x</device>
      <path>ict.moscow/removepreload</path>
      <browser>chrome</browser>
      <runCount>4</runCount>
    </run>
    <run runId="49">
      <device>nexus5x</device>
      <path>traineracademy.org/noremovepreload</path>
      <browser>chrome</browser>
      <runCount>5</runCount>
    </run>
    <run runId="384">
      <device>nexus5x</device>
      <path>parsely.com/removepreload</path>
      <browser>chrome</browser>
      <runCount>5</runCount>
    </run>
    <run runId="39">
      <device>nexus5x</device>
      <path>africafreak.com/noremovepreload</path>
      <browser>chrome</browser>
      <runCount>5</runCount>
    </run>
    <run runId="171">
      <device>nexus5x</device>
      <path>blistex.com/removepreload</path>
      <browser>chrome</browser>
      <runCount>2</runCount>
    </run>
    <run runId="209">
      <device>nexus5x</device>
      <path>ladbible.com/noremovepreload</path>
      <browser>chrome</browser>
      <runCount>5</runCount>
    </run>
    <run runId="100">
      <device>nexus5x</device>
      <path>musicgreatness.com/removepreload</path>
      <browser>chrome</browser>
      <runCount>1</runCount>
    </run>
    <run runId="288">
      <device>nexus5x</device>
      <path>affirm.com/noremovepreload</path>
      <browser>chrome</browser>
      <runCount>4</runCount>
    </run>
    <run runId="94">
      <device>nexus5x</device>
      <path>agriwebb.com/removepreload</path>
      <browser>chrome</browser>
      <runCount>5</runCount>
    </run>
    <run runId="187">
      <device>nexus5x</device>
      <path>fitchratings.ru/noremovepreload</path>
      <browser>chrome</browser>
      <runCount>3</runCount>
    </run>
    <run runId="19">
      <device>nexus5x</device>
      <path>squareinternet.co/noremovepreload</path>
      <browser>chrome</browser>
      <runCount>5</runCount>
    </run>
    <run runId="199">
      <device>nexus5x</device>
      <path>berlinomagazine.com/noremovepreload</path>
      <browser>chrome</browser>
      <runCount>5</runCount>
    </run>
    <run runId="230">
      <device>nexus5x</device>
      <path>beegru.com/removepreload</path>
      <browser>chrome</browser>
      <runCount>1</runCount>
    </run>
    <run runId="52">
      <device>nexus5x</device>
      <path>lisakristine.com/removepreload</path>
      <browser>chrome</browser>
      <runCount>3</runCount>
    </run>
    <run runId="160">
      <device>nexus5x</device>
      <path>animoto.com/removepreload</path>
      <browser>chrome</browser>
      <runCount>1</runCount>
    </run>
    <run runId="119">
      <device>nexus5x</device>
      <path>cbc.ca/noremovepreload</path>
      <browser>chrome</browser>
      <runCount>5</runCount>
    </run>
    <run runId="259">
      <device>nexus5x</device>
      <path>schmoozecom.com/noremovepreload</path>
      <browser>chrome</browser>
      <runCount>5</runCount>
    </run>
    <run runId="24">
      <device>nexus5x</device>
      <path>unilad.co.uk/removepreload</path>
      <browser>chrome</browser>
      <runCount>5</runCount>
    </run>
    <run runId="128">
      <device>nexus5x</device>
      <path>fastcodesign.com/noremovepreload</path>
      <browser>chrome</browser>
      <runCount>4</runCount>
    </run>
    <run runId="131">
      <device>nexus5x</device>
      <path>trustpilot.com/removepreload</path>
      <browser>chrome</browser>
      <runCount>2</runCount>
    </run>
    <run runId="103">
      <device>nexus5x</device>
      <path>musicgreatness.com/removepreload</path>
      <browser>chrome</browser>
      <runCount>4</runCount>
    </run>
    <run runId="336">
      <device>nexus5x</device>
      <path>unclesamsmisguidedchildren.com/noremovepreload</path>
      <browser>chrome</browser>
      <runCount>2</runCount>
    </run>
    <run runId="377">
      <device>nexus5x</device>
      <path>coindesk.com/noremovepreload</path>
      <browser>chrome</browser>
      <runCount>3</runCount>
    </run>
    <run runId="307">
      <device>nexus5x</device>
      <path>ict.moscow/noremovepreload</path>
      <browser>chrome</browser>
      <runCount>3</runCount>
    </run>
    <run runId="347">
      <device>nexus5x</device>
      <path>veronicatv.nl/noremovepreload</path>
      <browser>chrome</browser>
      <runCount>3</runCount>
    </run>
    <run runId="173">
      <device>nexus5x</device>
      <path>blistex.com/removepreload</path>
      <browser>chrome</browser>
      <runCount>4</runCount>
    </run>
    <run runId="215">
      <device>nexus5x</device>
      <path>infobunny.com/noremovepreload</path>
      <browser>chrome</browser>
      <runCount>1</runCount>
    </run>
    <run runId="381">
      <device>nexus5x</device>
      <path>parsely.com/removepreload</path>
      <browser>chrome</browser>
      <runCount>2</runCount>
    </run>
    <run runId="313">
      <device>nexus5x</device>
      <path>ingenieriareal.com/removepreload</path>
      <browser>chrome</browser>
      <runCount>4</runCount>
    </run>
    <run runId="338">
      <device>nexus5x</device>
      <path>unclesamsmisguidedchildren.com/noremovepreload</path>
      <browser>chrome</browser>
      <runCount>4</runCount>
    </run>
    <run runId="14">
      <device>nexus5x</device>
      <path>squareinternet.co/removepreload</path>
      <browser>chrome</browser>
      <runCount>5</runCount>
    </run>
    <run runId="0">
      <device>nexus5x</device>
      <path>bensonbingham.com/removepreload</path>
      <browser>chrome</browser>
      <runCount>1</runCount>
    </run>
    <run runId="40">
      <device>nexus5x</device>
      <path>traineracademy.org/removepreload</path>
      <browser>chrome</browser>
      <runCount>1</runCount>
    </run>
    <run runId="296">
      <device>nexus5x</device>
      <path>noshift.com/noremovepreload</path>
      <browser>chrome</browser>
      <runCount>2</runCount>
    </run>
    <run runId="241">
      <device>nexus5x</device>
      <path>scmp.com/removepreload</path>
      <browser>chrome</browser>
      <runCount>2</runCount>
    </run>
    <run runId="287">
      <device>nexus5x</device>
      <path>affirm.com/noremovepreload</path>
      <browser>chrome</browser>
      <runCount>3</runCount>
    </run>
    <run runId="130">
      <device>nexus5x</device>
      <path>trustpilot.com/removepreload</path>
      <browser>chrome</browser>
      <runCount>1</runCount>
    </run>
    <run runId="260">
      <device>nexus5x</device>
      <path>jisr.net/removepreload</path>
      <browser>chrome</browser>
      <runCount>1</runCount>
    </run>
    <run runId="141">
      <device>nexus5x</device>
      <path>theodysseyonline.com/removepreload</path>
      <browser>chrome</browser>
      <runCount>2</runCount>
    </run>
    <run runId="359">
      <device>nexus5x</device>
      <path>sedanmed.ir/noremovepreload</path>
      <browser>chrome</browser>
      <runCount>5</runCount>
    </run>
    <run runId="277">
      <device>nexus5x</device>
      <path>g-talent.net/noremovepreload</path>
      <browser>chrome</browser>
      <runCount>3</runCount>
    </run>
    <run runId="361">
      <device>nexus5x</device>
      <path>newsbreak.com/removepreload</path>
      <browser>chrome</browser>
      <runCount>2</runCount>
    </run>
    <run runId="357">
      <device>nexus5x</device>
      <path>sedanmed.ir/noremovepreload</path>
      <browser>chrome</browser>
      <runCount>3</runCount>
    </run>
    <run runId="22">
      <device>nexus5x</device>
      <path>unilad.co.uk/removepreload</path>
      <browser>chrome</browser>
      <runCount>3</runCount>
    </run>
    <run runId="265">
      <device>nexus5x</device>
      <path>jisr.net/noremovepreload</path>
      <browser>chrome</browser>
      <runCount>1</runCount>
    </run>
    <run runId="107">
      <device>nexus5x</device>
      <path>musicgreatness.com/noremovepreload</path>
      <browser>chrome</browser>
      <runCount>3</runCount>
    </run>
    <run runId="392">
      <device>nexus5x</device>
      <path>grantthornton.se/removepreload</path>
      <browser>chrome</browser>
      <runCount>3</runCount>
    </run>
    <run runId="122">
      <device>nexus5x</device>
      <path>fastcodesign.com/removepreload</path>
      <browser>chrome</browser>
      <runCount>3</runCount>
    </run>
    <run runId="217">
      <device>nexus5x</device>
      <path>infobunny.com/noremovepreload</path>
      <browser>chrome</browser>
      <runCount>3</runCount>
    </run>
    <run runId="2">
      <device>nexus5x</device>
      <path>bensonbingham.com/removepreload</path>
      <browser>chrome</browser>
      <runCount>3</runCount>
    </run>
    <run runId="185">
      <device>nexus5x</device>
      <path>fitchratings.ru/noremovepreload</path>
      <browser>chrome</browser>
      <runCount>1</runCount>
    </run>
    <run runId="89">
      <device>nexus5x</device>
      <path>nbc.com/noremovepreload</path>
      <browser>chrome</browser>
      <runCount>5</runCount>
    </run>
    <run runId="58">
      <device>nexus5x</device>
      <path>lisakristine.com/noremovepreload</path>
      <browser>chrome</browser>
      <runCount>4</runCount>
    </run>
    <run runId="263">
      <device>nexus5x</device>
      <path>jisr.net/removepreload</path>
      <browser>chrome</browser>
      <runCount>4</runCount>
    </run>
    <run runId="180">
      <device>nexus5x</device>
      <path>fitchratings.ru/removepreload</path>
      <browser>chrome</browser>
      <runCount>1</runCount>
    </run>
    <run runId="163">
      <device>nexus5x</device>
      <path>animoto.com/removepreload</path>
      <browser>chrome</browser>
      <runCount>4</runCount>
    </run>
    <run runId="376">
      <device>nexus5x</device>
      <path>coindesk.com/noremovepreload</path>
      <browser>chrome</browser>
      <runCount>2</runCount>
    </run>
    <run runId="245">
      <device>nexus5x</device>
      <path>scmp.com/noremovepreload</path>
      <browser>chrome</browser>
      <runCount>1</runCount>
    </run>
    <run runId="212">
      <device>nexus5x</device>
      <path>infobunny.com/removepreload</path>
      <browser>chrome</browser>
      <runCount>3</runCount>
    </run>
    <run runId="330">
      <device>nexus5x</device>
      <path>unclesamsmisguidedchildren.com/removepreload</path>
      <browser>chrome</browser>
      <runCount>1</runCount>
    </run>
    <run runId="104">
      <device>nexus5x</device>
      <path>musicgreatness.com/removepreload</path>
      <browser>chrome</browser>
      <runCount>5</runCount>
    </run>
    <run runId="77">
      <device>nexus5x</device>
      <path>screenrant.com/noremovepreload</path>
      <browser>chrome</browser>
      <runCount>3</runCount>
    </run>
    <run runId="162">
      <device>nexus5x</device>
      <path>animoto.com/removepreload</path>
      <browser>chrome</browser>
      <runCount>3</runCount>
    </run>
    <run runId="337">
      <device>nexus5x</device>
      <path>unclesamsmisguidedchildren.com/noremovepreload</path>
      <browser>chrome</browser>
      <runCount>3</runCount>
    </run>
  <run runId="375">
      <device>nexus5x</device>
      <path>coindesk.com/noremovepreload</path>
      <browser>chrome</browser>
      <runCount>1</runCount>
    </run>
    <run runId="70">
      <device>nexus5x</device>
      <path>screenrant.com/removepreload</path>
      <browser>chrome</browser>
      <runCount>1</runCount>
    </run>
    <run runId="293">
      <device>nexus5x</device>
      <path>noshift.com/removepreload</path>
      <browser>chrome</browser>
      <runCount>4</runCount>
    </run>
    <run runId="364">
      <device>nexus5x</device>
      <path>newsbreak.com/removepreload</path>
      <browser>chrome</browser>
      <runCount>5</runCount>
    </run>
    <run runId="195">
      <device>nexus5x</device>
      <path>berlinomagazine.com/noremovepreload</path>
      <browser>chrome</browser>
      <runCount>1</runCount>
    </run>
    <run runId="21">
      <device>nexus5x</device>
      <path>unilad.co.uk/removepreload</path>
      <browser>chrome</browser>
      <runCount>2</runCount>
    </run>
    <run runId="54">
      <device>nexus5x</device>
      <path>lisakristine.com/removepreload</path>
      <browser>chrome</browser>
      <runCount>5</runCount>
    </run>
    <run runId="247">
      <device>nexus5x</device>
      <path>scmp.com/noremovepreload</path>
      <browser>chrome</browser>
      <runCount>3</runCount>
    </run>
    <run runId="210">
      <device>nexus5x</device>
      <path>infobunny.com/removepreload</path>
      <browser>chrome</browser>
      <runCount>1</runCount>
    </run>
    <run runId="218">
      <device>nexus5x</device>
      <path>infobunny.com/noremovepreload</path>
      <browser>chrome</browser>
      <runCount>4</runCount>
    </run>
    <run runId="233">
      <device>nexus5x</device>
      <path>beegru.com/removepreload</path>
      <browser>chrome</browser>
      <runCount>4</runCount>
    </run>
    <run runId="98">
      <device>nexus5x</device>
      <path>agriwebb.com/noremovepreload</path>
      <browser>chrome</browser>
      <runCount>4</runCount>
    </run>
    <run runId="226">
      <device>nexus5x</device>
      <path>intercom.io/noremovepreload</path>
      <browser>chrome</browser>
      <runCount>2</runCount>
    </run>
    <run runId="252">
      <device>nexus5x</device>
      <path>schmoozecom.com/removepreload</path>
      <browser>chrome</browser>
      <runCount>3</runCount>
    </run>
    <run runId="266">
      <device>nexus5x</device>
      <path>jisr.net/noremovepreload</path>
      <browser>chrome</browser>
      <runCount>2</runCount>
    </run>
    <run runId="35">
      <device>nexus5x</device>
      <path>africafreak.com/noremovepreload</path>
      <browser>chrome</browser>
      <runCount>1</runCount>
    </run>
    <run runId="59">
      <device>nexus5x</device>
      <path>lisakristine.com/noremovepreload</path>
      <browser>chrome</browser>
      <runCount>5</runCount>
    </run>
    <run runId="366">
      <device>nexus5x</device>
      <path>newsbreak.com/noremovepreload</path>
      <browser>chrome</browser>
      <runCount>2</runCount>
    </run>
    <run runId="324">
      <device>nexus5x</device>
      <path>sportbible.com/removepreload</path>
      <browser>chrome</browser>
      <runCount>5</runCount>
    </run>
    <run runId="237">
      <device>nexus5x</device>
      <path>beegru.com/noremovepreload</path>
      <browser>chrome</browser>
      <runCount>3</runCount>
    </run>
    <run runId="395">
      <device>nexus5x</device>
      <path>grantthornton.se/noremovepreload</path>
      <browser>chrome</browser>
      <runCount>1</runCount>
    </run>
    <run runId="7">
      <device>nexus5x</device>
      <path>bensonbingham.com/noremovepreload</path>
      <browser>chrome</browser>
      <runCount>3</runCount>
    </run>
    <run runId="12">
      <device>nexus5x</device>
      <path>squareinternet.co/removepreload</path>
      <browser>chrome</browser>
      <runCount>3</runCount>
    </run>
    <run runId="228">
      <device>nexus5x</device>
      <path>intercom.io/noremovepreload</path>
      <browser>chrome</browser>
      <runCount>4</runCount>
    </run>
    <run runId="137">
      <device>nexus5x</device>
      <path>trustpilot.com/noremovepreload</path>
      <browser>chrome</browser>
      <runCount>3</runCount>
    </run>
    <run runId="114">
      <device>nexus5x</device>
      <path>cbc.ca/removepreload</path>
      <browser>chrome</browser>
      <runCount>5</runCount>
    </run>
    <run runId="356">
      <device>nexus5x</device>
      <path>sedanmed.ir/noremovepreload</path>
      <browser>chrome</browser>
      <runCount>2</runCount>
    </run>
    <run runId="32">
      <device>nexus5x</device>
      <path>africafreak.com/removepreload</path>
      <browser>chrome</browser>
      <runCount>3</runCount>
    </run>
    <run runId="112">
      <device>nexus5x</device>
      <path>cbc.ca/removepreload</path>
      <browser>chrome</browser>
      <runCount>3</runCount>
    </run>
    <run runId="84">
      <device>nexus5x</device>
      <path>nbc.com/removepreload</path>
      <browser>chrome</browser>
      <runCount>5</runCount>
    </run>
    <run runId="186">
      <device>nexus5x</device>
      <path>fitchratings.ru/noremovepreload</path>
      <browser>chrome</browser>
      <runCount>2</runCount>
    </run>
    <run runId="284">
      <device>nexus5x</device>
      <path>affirm.com/removepreload</path>
      <browser>chrome</browser>
      <runCount>5</runCount>
    </run>
    <run runId="133">
      <device>nexus5x</device>
      <path>trustpilot.com/removepreload</path>
      <browser>chrome</browser>
      <runCount>4</runCount>
    </run>
    <run runId="29">
      <device>nexus5x</device>
      <path>unilad.co.uk/noremovepreload</path>
      <browser>chrome</browser>
      <runCount>5</runCount>
    </run>
    <run runId="325">
      <device>nexus5x</device>
      <path>sportbible.com/noremovepreload</path>
      <browser>chrome</browser>
      <runCount>1</runCount>
    </run>
    <run runId="281">
      <device>nexus5x</device>
      <path>affirm.com/removepreload</path>
      <browser>chrome</browser>
      <runCount>2</runCount>
    </run>
    <run runId="202">
      <device>nexus5x</device>
      <path>ladbible.com/removepreload</path>
      <browser>chrome</browser>
      <runCount>3</runCount>
    </run>
    <run runId="176">
      <device>nexus5x</device>
      <path>blistex.com/noremovepreload</path>
      <browser>chrome</browser>
      <runCount>2</runCount>
    </run>
    <run runId="354">
      <device>nexus5x</device>
      <path>sedanmed.ir/removepreload</path>
      <browser>chrome</browser>
      <runCount>5</runCount>
    </run>
    <run runId="152">
      <device>nexus5x</device>
      <path>dji.com/removepreload</path>
      <browser>chrome</browser>
      <runCount>3</runCount>
    </run>
    <run runId="193">
      <device>nexus5x</device>
      <path>berlinomagazine.com/removepreload</path>
      <browser>chrome</browser>
      <runCount>4</runCount>
    </run>
    <run runId="349">
      <device>nexus5x</device>
      <path>veronicatv.nl/noremovepreload</path>
      <browser>chrome</browser>
      <runCount>5</runCount>
    </run>
    <run runId="86">
      <device>nexus5x</device>
      <path>nbc.com/noremovepreload</path>
      <browser>chrome</browser>
      <runCount>2</runCount>
    </run>
    <run runId="221">
      <device>nexus5x</device>
      <path>intercom.io/removepreload</path>
      <browser>chrome</browser>
      <runCount>2</runCount>
    </run>
    <run runId="135">
      <device>nexus5x</device>
      <path>trustpilot.com/noremovepreload</path>
      <browser>chrome</browser>
      <runCount>1</runCount>
    </run>
    <run runId="320">
      <device>nexus5x</device>
      <path>sportbible.com/removepreload</path>
      <browser>chrome</browser>
      <runCount>1</runCount>
    </run>
    <run runId="355">
      <device>nexus5x</device>
      <path>sedanmed.ir/noremovepreload</path>
      <browser>chrome</browser>
      <runCount>1</runCount>
    </run>
    <run runId="224">
      <device>nexus5x</device>
      <path>intercom.io/removepreload</path>
      <browser>chrome</browser>
      <runCount>5</runCount>
    </run>
    <run runId="189">
      <device>nexus5x</device>
      <path>fitchratings.ru/noremovepreload</path>
      <browser>chrome</browser>
      <runCount>5</runCount>
    </run>
    <run runId="329">
      <device>nexus5x</device>
      <path>sportbible.com/noremovepreload</path>
      <browser>chrome</browser>
      <runCount>5</runCount>
    </run>
    <run runId="61">
      <device>nexus5x</device>
      <path>home.pl/removepreload</path>
      <browser>chrome</browser>
      <runCount>2</runCount>
    </run>
    <run runId="390">
      <device>nexus5x</device>
      <path>grantthornton.se/removepreload</path>
      <browser>chrome</browser>
      <runCount>1</runCount>
    </run>
    <run runId="18">
      <device>nexus5x</device>
      <path>squareinternet.co/noremovepreload</path>
      <browser>chrome</browser>
      <runCount>4</runCount>
    </run>
    <run runId="192">
      <device>nexus5x</device>
      <path>berlinomagazine.com/removepreload</path>
      <browser>chrome</browser>
      <runCount>3</runCount>
    </run>
    <run runId="8">
      <device>nexus5x</device>
      <path>bensonbingham.com/noremovepreload</path>
      <browser>chrome</browser>
      <runCount>4</runCount>
    </run>
    <run runId="177">
      <device>nexus5x</device>
      <path>blistex.com/noremovepreload</path>
      <browser>chrome</browser>
      <runCount>3</runCount>
    </run>
    <run runId="345">
      <device>nexus5x</device>
      <path>veronicatv.nl/noremovepreload</path>
      <browser>chrome</browser>
      <runCount>1</runCount>
    </run>
    <run runId="71">
      <device>nexus5x</device>
      <path>screenrant.com/removepreload</path>
      <browser>chrome</browser>
      <runCount>2</runCount>
    </run>
    <run runId="34">
      <device>nexus5x</device>
      <path>africafreak.com/removepreload</path>
      <browser>chrome</browser>
      <runCount>5</runCount>
    </run>
    <run runId="291">
      <device>nexus5x</device>
      <path>noshift.com/removepreload</path>
      <browser>chrome</browser>
      <runCount>2</runCount>
    </run>
    <run runId="346">
      <device>nexus5x</device>
      <path>veronicatv.nl/noremovepreload</path>
      <browser>chrome</browser>
      <runCount>2</runCount>
    </run>
    <run runId="398">
      <device>nexus5x</device>
      <path>grantthornton.se/noremovepreload</path>
      <browser>chrome</browser>
      <runCount>4</runCount>
    </run>
    <run runId="220">
      <device>nexus5x</device>
      <path>intercom.io/removepreload</path>
      <browser>chrome</browser>
      <runCount>1</runCount>
    </run>
    <run runId="91">
      <device>nexus5x</device>
      <path>agriwebb.com/removepreload</path>
      <browser>chrome</browser>
      <runCount>2</runCount>
    </run>
    <run runId="222">
      <device>nexus5x</device>
      <path>intercom.io/removepreload</path>
      <browser>chrome</browser>
      <runCount>3</runCount>
    </run>
    <run runId="16">
      <device>nexus5x</device>
      <path>squareinternet.co/noremovepreload</path>
      <browser>chrome</browser>
      <runCount>2</runCount>
    </run>
    <run runId="270">
      <device>nexus5x</device>
      <path>g-talent.net/removepreload</path>
      <browser>chrome</browser>
      <runCount>1</runCount>
    </run>
    <run runId="362">
      <device>nexus5x</device>
      <path>newsbreak.com/removepreload</path>
      <browser>chrome</browser>
      <runCount>3</runCount>
    </run>
    <run runId="383">
      <device>nexus5x</device>
      <path>parsely.com/removepreload</path>
      <browser>chrome</browser>
      <runCount>4</runCount>
    </run>
    <run runId="90">
      <device>nexus5x</device>
      <path>agriwebb.com/removepreload</path>
      <browser>chrome</browser>
      <runCount>1</runCount>
    </run>
    <run runId="397">
      <device>nexus5x</device>
      <path>grantthornton.se/noremovepreload</path>
      <browser>chrome</browser>
      <runCount>3</runCount>
    </run>
    <run runId="204">
      <device>nexus5x</device>
      <path>ladbible.com/removepreload</path>
      <browser>chrome</browser>
      <runCount>5</runCount>
    </run>
    <run runId="283">
      <device>nexus5x</device>
      <path>affirm.com/removepreload</path>
      <browser>chrome</browser>
      <runCount>4</runCount>
    </run>
    <run runId="351">
      <device>nexus5x</device>
      <path>sedanmed.ir/removepreload</path>
      <browser>chrome</browser>
      <runCount>2</runCount>
    </run>
    <run runId="190">
      <device>nexus5x</device>
      <path>berlinomagazine.com/removepreload</path>
      <browser>chrome</browser>
      <runCount>1</runCount>
    </run>
    <run runId="206">
      <device>nexus5x</device>
      <path>ladbible.com/noremovepreload</path>
      <browser>chrome</browser>
      <runCount>2</runCount>
    </run>
    <run runId="3">
      <device>nexus5x</device>
      <path>bensonbingham.com/removepreload</path>
      <browser>chrome</browser>
      <runCount>4</runCount>
    </run>
    <run runId="138">
      <device>nexus5x</device>
      <path>trustpilot.com/noremovepreload</path>
      <browser>chrome</browser>
      <runCount>4</runCount>
    </run>
    <run runId="167">
      <device>nexus5x</device>
      <path>animoto.com/noremovepreload</path>
      <browser>chrome</browser>
      <runCount>3</runCount>
    </run>
    <run runId="321">
      <device>nexus5x</device>
      <path>sportbible.com/removepreload</path>
      <browser>chrome</browser>
      <runCount>2</runCount>
    </run>
    <run runId="194">
      <device>nexus5x</device>
      <path>berlinomagazine.com/removepreload</path>
      <browser>chrome</browser>
      <runCount>5</runCount>
    </run>
    <run runId="60">
      <device>nexus5x</device>
      <path>home.pl/removepreload</path>
      <browser>chrome</browser>
      <runCount>1</runCount>
    </run>
    <run runId="396">
      <device>nexus5x</device>
      <path>grantthornton.se/noremovepreload</path>
      <browser>chrome</browser>
      <runCount>2</runCount>
    </run>
    <run runId="316">
      <device>nexus5x</device>
      <path>ingenieriareal.com/noremovepreload</path>
      <browser>chrome</browser>
      <runCount>2</runCount>
    </run>
    <run runId="358">
      <device>nexus5x</device>
      <path>sedanmed.ir/noremovepreload</path>
      <browser>chrome</browser>
      <runCount>4</runCount>
    </run>
    <run runId="227">
      <device>nexus5x</device>
      <path>intercom.io/noremovepreload</path>
      <browser>chrome</browser>
      <runCount>3</runCount>
    </run>
    <run runId="391">
      <device>nexus5x</device>
      <path>grantthornton.se/removepreload</path>
      <browser>chrome</browser>
      <runCount>2</runCount>
    </run>
    <run runId="368">
      <device>nexus5x</device>
      <path>newsbreak.com/noremovepreload</path>
      <browser>chrome</browser>
      <runCount>4</runCount>
    </run>
    <run runId="76">
      <device>nexus5x</device>
      <path>screenrant.com/noremovepreload</path>
      <browser>chrome</browser>
      <runCount>2</runCount>
    </run>
    <run runId="106">
      <device>nexus5x</device>
      <path>musicgreatness.com/noremovepreload</path>
      <browser>chrome</browser>
      <runCount>2</runCount>
    </run>
    <run runId="95">
      <device>nexus5x</device>
      <path>agriwebb.com/noremovepreload</path>
      <browser>chrome</browser>
      <runCount>1</runCount>
    </run>
    <run runId="213">
      <device>nexus5x</device>
      <path>infobunny.com/removepreload</path>
      <browser>chrome</browser>
      <runCount>4</runCount>
    </run>
    <run runId="201">
      <device>nexus5x</device>
      <path>ladbible.com/removepreload</path>
      <browser>chrome</browser>
      <runCount>2</runCount>
    </run>
    <run runId="386">
      <device>nexus5x</device>
      <path>parsely.com/noremovepreload</path>
      <browser>chrome</browser>
      <runCount>2</runCount>
    </run>
    <run runId="240">
      <device>nexus5x</device>
      <path>scmp.com/removepreload</path>
      <browser>chrome</browser>
      <runCount>1</runCount>
    </run>
    <run runId="299">
      <device>nexus5x</device>
      <path>noshift.com/noremovepreload</path>
      <browser>chrome</browser>
      <runCount>5</runCount>
    </run>
    <run runId="271">
      <device>nexus5x</device>
      <path>g-talent.net/removepreload</path>
      <browser>chrome</browser>
      <runCount>2</runCount>
    </run>
    <run runId="261">
      <device>nexus5x</device>
      <path>jisr.net/removepreload</path>
      <browser>chrome</browser>
      <runCount>2</runCount>
    </run>
    <run runId="234">
      <device>nexus5x</device>
      <path>beegru.com/removepreload</path>
      <browser>chrome</browser>
      <runCount>5</runCount>
    </run>
    <run runId="125">
      <device>nexus5x</device>
      <path>fastcodesign.com/noremovepreload</path>
      <browser>chrome</browser>
      <runCount>1</runCount>
    </run>
    <run runId="297">
      <device>nexus5x</device>
      <path>noshift.com/noremovepreload</path>
      <browser>chrome</browser>
      <runCount>3</runCount>
    </run>
    <run runId="30">
      <device>nexus5x</device>
      <path>africafreak.com/removepreload</path>
      <browser>chrome</browser>
      <runCount>1</runCount>
    </run>
    <run runId="282">
      <device>nexus5x</device>
      <path>affirm.com/removepreload</path>
      <browser>chrome</browser>
      <runCount>3</runCount>
    </run>
    <run runId="6">
      <device>nexus5x</device>
      <path>bensonbingham.com/noremovepreload</path>
      <browser>chrome</browser>
      <runCount>2</runCount>
    </run>
    <run runId="80">
      <device>nexus5x</device>
      <path>nbc.com/removepreload</path>
      <browser>chrome</browser>
      <runCount>1</runCount>
    </run>
    <run runId="242">
      <device>nexus5x</device>
      <path>scmp.com/removepreload</path>
      <browser>chrome</browser>
      <runCount>3</runCount>
    </run>
    <run runId="15">
      <device>nexus5x</device>
      <path>squareinternet.co/noremovepreload</path>
      <browser>chrome</browser>
      <runCount>1</runCount>
    </run>
    <run runId="115">
      <device>nexus5x</device>
      <path>cbc.ca/noremovepreload</path>
      <browser>chrome</browser>
      <runCount>1</runCount>
    </run>
    <run runId="158">
      <device>nexus5x</device>
      <path>dji.com/noremovepreload</path>
      <browser>chrome</browser>
      <runCount>4</runCount>
    </run>
    <run runId="348">
      <device>nexus5x</device>
      <path>veronicatv.nl/noremovepreload</path>
      <browser>chrome</browser>
      <runCount>4</runCount>
    </run>
    <run runId="328">
      <device>nexus5x</device>
      <path>sportbible.com/noremovepreload</path>
      <browser>chrome</browser>
      <runCount>4</runCount>
    </run>
    <run runId="53">
      <device>nexus5x</device>
      <path>lisakristine.com/removepreload</path>
      <browser>chrome</browser>
      <runCount>4</runCount>
    </run>
    <run runId="184">
      <device>nexus5x</device>
      <path>fitchratings.ru/removepreload</path>
      <browser>chrome</browser>
      <runCount>5</runCount>
    </run>
    <run runId="198">
      <device>nexus5x</device>
      <path>berlinomagazine.com/noremovepreload</path>
      <browser>chrome</browser>
      <runCount>4</runCount>
    </run>
    <run runId="73">
      <device>nexus5x</device>
      <path>screenrant.com/removepreload</path>
      <browser>chrome</browser>
      <runCount>4</runCount>
    </run>
    <run runId="207">
      <device>nexus5x</device>
      <path>ladbible.com/noremovepreload</path>
      <browser>chrome</browser>
      <runCount>3</runCount>
    </run>
    <run runId="292">
      <device>nexus5x</device>
      <path>noshift.com/removepreload</path>
      <browser>chrome</browser>
      <runCount>3</runCount>
    </run>
    <run runId="146">
      <device>nexus5x</device>
      <path>theodysseyonline.com/noremovepreload</path>
      <browser>chrome</browser>
      <runCount>2</runCount>
    </run>
    <run runId="67">
      <device>nexus5x</device>
      <path>home.pl/noremovepreload</path>
      <browser>chrome</browser>
      <runCount>3</runCount>
    </run>
    <run runId="75">
      <device>nexus5x</device>
      <path>screenrant.com/noremovepreload</path>
      <browser>chrome</browser>
      <runCount>1</runCount>
    </run>
    <run runId="225">
      <device>nexus5x</device>
      <path>intercom.io/noremovepreload</path>
      <browser>chrome</browser>
      <runCount>1</runCount>
    </run>
    <run runId="278">
      <device>nexus5x</device>
      <path>g-talent.net/noremovepreload</path>
      <browser>chrome</browser>
      <runCount>4</runCount>
    </run>
    <run runId="326">
      <device>nexus5x</device>
      <path>sportbible.com/noremovepreload</path>
      <browser>chrome</browser>
      <runCount>2</runCount>
    </run>
    <run runId="82">
      <device>nexus5x</device>
      <path>nbc.com/removepreload</path>
      <browser>chrome</browser>
      <runCount>3</runCount>
    </run>
    <run runId="140">
      <device>nexus5x</device>
      <path>theodysseyonline.com/removepreload</path>
      <browser>chrome</browser>
      <runCount>1</runCount>
    </run>
    <run runId="170">
      <device>nexus5x</device>
      <path>blistex.com/removepreload</path>
      <browser>chrome</browser>
      <runCount>1</runCount>
    </run>
    <run runId="286">
      <device>nexus5x</device>
      <path>affirm.com/noremovepreload</path>
      <browser>chrome</browser>
      <runCount>2</runCount>
    </run>
    <run runId="17">
      <device>nexus5x</device>
      <path>squareinternet.co/noremovepreload</path>
      <browser>chrome</browser>
      <runCount>3</runCount>
    </run>
    <run runId="367">
      <device>nexus5x</device>
      <path>newsbreak.com/noremovepreload</path>
      <browser>chrome</browser>
      <runCount>3</runCount>
    </run>
    <run runId="120">
      <device>nexus5x</device>
      <path>fastcodesign.com/removepreload</path>
      <browser>chrome</browser>
      <runCount>1</runCount>
    </run>
    <run runId="335">
      <device>nexus5x</device>
      <path>unclesamsmisguidedchildren.com/noremovepreload</path>
      <browser>chrome</browser>
      <runCount>1</runCount>
    </run>
    <run runId="352">
      <device>nexus5x</device>
      <path>sedanmed.ir/removepreload</path>
      <browser>chrome</browser>
      <runCount>3</runCount>
    </run>
    <run runId="219">
      <device>nexus5x</device>
      <path>infobunny.com/noremovepreload</path>
      <browser>chrome</browser>
      <runCount>5</runCount>
    </run>
    <run runId="382">
      <device>nexus5x</device>
      <path>parsely.com/removepreload</path>
      <browser>chrome</browser>
      <runCount>3</runCount>
    </run>
    <run runId="26">
      <device>nexus5x</device>
      <path>unilad.co.uk/noremovepreload</path>
      <browser>chrome</browser>
      <runCount>2</runCount>
    </run>
    <run runId="168">
      <device>nexus5x</device>
      <path>animoto.com/noremovepreload</path>
      <browser>chrome</browser>
      <runCount>4</runCount>
    </run>
    <run runId="191">
      <device>nexus5x</device>
      <path>berlinomagazine.com/removepreload</path>
      <browser>chrome</browser>
      <runCount>2</runCount>
    </run>
    <run runId="25">
      <device>nexus5x</device>
      <path>unilad.co.uk/noremovepreload</path>
      <browser>chrome</browser>
      <runCount>1</runCount>
    </run>
    <run runId="139">
      <device>nexus5x</device>
      <path>trustpilot.com/noremovepreload</path>
      <browser>chrome</browser>
      <runCount>5</runCount>
    </run>
    <run runId="334">
      <device>nexus5x</device>
      <path>unclesamsmisguidedchildren.com/removepreload</path>
      <browser>chrome</browser>
      <runCount>5</runCount>
    </run>
    <run runId="264">
      <device>nexus5x</device>
      <path>jisr.net/removepreload</path>
      <browser>chrome</browser>
      <runCount>5</runCount>
    </run>
    <run runId="105">
      <device>nexus5x</device>
      <path>musicgreatness.com/noremovepreload</path>
      <browser>chrome</browser>
      <runCount>1</runCount>
    </run>
    <run runId="56">
      <device>nexus5x</device>
      <path>lisakristine.com/noremovepreload</path>
      <browser>chrome</browser>
      <runCount>2</runCount>
    </run>
    <run runId="66">
      <device>nexus5x</device>
      <path>home.pl/noremovepreload</path>
      <browser>chrome</browser>
      <runCount>2</runCount>
    </run>
    <run runId="294">
      <device>nexus5x</device>
      <path>noshift.com/removepreload</path>
      <browser>chrome</browser>
      <runCount>5</runCount>
    </run>
    <run runId="147">
      <device>nexus5x</device>
      <path>theodysseyonline.com/noremovepreload</path>
      <browser>chrome</browser>
      <runCount>3</runCount>
    </run>
    <run runId="161">
      <device>nexus5x</device>
      <path>animoto.com/removepreload</path>
      <browser>chrome</browser>
      <runCount>2</runCount>
    </run>
    <run runId="274">
      <device>nexus5x</device>
      <path>g-talent.net/removepreload</path>
      <browser>chrome</browser>
      <runCount>5</runCount>
    </run>
    <run runId="31">
      <device>nexus5x</device>
      <path>africafreak.com/removepreload</path>
      <browser>chrome</browser>
      <runCount>2</runCount>
    </run>
    <run runId="371">
      <device>nexus5x</device>
      <path>coindesk.com/removepreload</path>
      <browser>chrome</browser>
      <runCount>2</runCount>
    </run>
    <run runId="340">
      <device>nexus5x</device>
      <path>veronicatv.nl/removepreload</path>
      <browser>chrome</browser>
      <runCount>1</runCount>
    </run>
    <run runId="350">
      <device>nexus5x</device>
      <path>sedanmed.ir/removepreload</path>
      <browser>chrome</browser>
      <runCount>1</runCount>
    </run>
    <run runId="144">
      <device>nexus5x</device>
      <path>theodysseyonline.com/removepreload</path>
      <browser>chrome</browser>
      <runCount>5</runCount>
    </run>
    <run runId="268">
      <device>nexus5x</device>
      <path>jisr.net/noremovepreload</path>
      <browser>chrome</browser>
      <runCount>4</runCount>
    </run>
    <run runId="110">
      <device>nexus5x</device>
      <path>cbc.ca/removepreload</path>
      <browser>chrome</browser>
      <runCount>1</runCount>
    </run>
    <run runId="126">
      <device>nexus5x</device>
      <path>fastcodesign.com/noremovepreload</path>
      <browser>chrome</browser>
      <runCount>2</runCount>
    </run>
    <run runId="232">
      <device>nexus5x</device>
      <path>beegru.com/removepreload</path>
      <browser>chrome</browser>
      <runCount>3</runCount>
    </run>
    <run runId="343">
      <device>nexus5x</device>
      <path>veronicatv.nl/removepreload</path>
      <browser>chrome</browser>
      <runCount>4</runCount>
    </run>
    <run runId="370">
      <device>nexus5x</device>
      <path>coindesk.com/removepreload</path>
      <browser>chrome</browser>
      <runCount>1</runCount>
    </run>
    <run runId="327">
      <device>nexus5x</device>
      <path>sportbible.com/noremovepreload</path>
      <browser>chrome</browser>
      <runCount>3</runCount>
    </run>
    <run runId="57">
      <device>nexus5x</device>
      <path>lisakristine.com/noremovepreload</path>
      <browser>chrome</browser>
      <runCount>3</runCount>
    </run>
    <run runId="74">
      <device>nexus5x</device>
      <path>screenrant.com/removepreload</path>
      <browser>chrome</browser>
      <runCount>5</runCount>
    </run>
    <run runId="172">
      <device>nexus5x</device>
      <path>blistex.com/removepreload</path>
      <browser>chrome</browser>
      <runCount>3</runCount>
    </run>
    <run runId="33">
      <device>nexus5x</device>
      <path>africafreak.com/removepreload</path>
      <browser>chrome</browser>
      <runCount>4</runCount>
    </run>
    <run runId="188">
      <device>nexus5x</device>
      <path>fitchratings.ru/noremovepreload</path>
      <browser>chrome</browser>
      <runCount>4</runCount>
    </run>
    <run runId="101">
      <device>nexus5x</device>
      <path>musicgreatness.com/removepreload</path>
      <browser>chrome</browser>
      <runCount>2</runCount>
    </run>
    <run runId="235">
      <device>nexus5x</device>
      <path>beegru.com/noremovepreload</path>
      <browser>chrome</browser>
      <runCount>1</runCount>
    </run>
    <run runId="253">
      <device>nexus5x</device>
      <path>schmoozecom.com/removepreload</path>
      <browser>chrome</browser>
      <runCount>4</runCount>
    </run>
    <run runId="151">
      <device>nexus5x</device>
      <path>dji.com/removepreload</path>
      <browser>chrome</browser>
      <runCount>2</runCount>
    </run>
    <run runId="302">
      <device>nexus5x</device>
      <path>ict.moscow/removepreload</path>
      <browser>chrome</browser>
      <runCount>3</runCount>
    </run>
    <run runId="47">
      <device>nexus5x</device>
      <path>traineracademy.org/noremovepreload</path>
      <browser>chrome</browser>
      <runCount>3</runCount>
    </run>
    <run runId="13">
      <device>nexus5x</device>
      <path>squareinternet.co/removepreload</path>
      <browser>chrome</browser>
      <runCount>4</runCount>
    </run>
    <run runId="310">
      <device>nexus5x</device>
      <path>ingenieriareal.com/removepreload</path>
      <browser>chrome</browser>
      <runCount>1</runCount>
    </run>
    <run runId="42">
      <device>nexus5x</device>
      <path>traineracademy.org/removepreload</path>
      <browser>chrome</browser>
      <runCount>3</runCount>
    </run>
    <run runId="374">
      <device>nexus5x</device>
      <path>coindesk.com/removepreload</path>
      <browser>chrome</browser>
      <runCount>5</runCount>
    </run>
    <run runId="280">
      <device>nexus5x</device>
      <path>affirm.com/removepreload</path>
      <browser>chrome</browser>
      <runCount>1</runCount>
    </run>
    <run runId="111">
      <device>nexus5x</device>
      <path>cbc.ca/removepreload</path>
      <browser>chrome</browser>
      <runCount>2</runCount>
    </run>
    <run runId="331">
      <device>nexus5x</device>
      <path>unclesamsmisguidedchildren.com/removepreload</path>
      <browser>chrome</browser>
      <runCount>2</runCount>
    </run>
    <run runId="200">
      <device>nexus5x</device>
      <path>ladbible.com/removepreload</path>
      <browser>chrome</browser>
      <runCount>1</runCount>
    </run>
    <run runId="108">
      <device>nexus5x</device>
      <path>musicgreatness.com/noremovepreload</path>
      <browser>chrome</browser>
      <runCount>4</runCount>
    </run>
    <run runId="48">
      <device>nexus5x</device>
      <path>traineracademy.org/noremovepreload</path>
      <browser>chrome</browser>
      <runCount>4</runCount>
    </run>
    <run runId="258">
      <device>nexus5x</device>
      <path>schmoozecom.com/noremovepreload</path>
      <browser>chrome</browser>
      <runCount>4</runCount>
    </run>
    <run runId="37">
      <device>nexus5x</device>
      <path>africafreak.com/noremovepreload</path>
      <browser>chrome</browser>
      <runCount>3</runCount>
    </run>
    <run runId="149">
      <device>nexus5x</device>
      <path>theodysseyonline.com/noremovepreload</path>
      <browser>chrome</browser>
      <runCount>5</runCount>
    </run>
    <run runId="109">
      <device>nexus5x</device>
      <path>musicgreatness.com/noremovepreload</path>
      <browser>chrome</browser>
      <runCount>5</runCount>
    </run>
    <run runId="214">
      <device>nexus5x</device>
      <path>infobunny.com/removepreload</path>
      <browser>chrome</browser>
      <runCount>5</runCount>
    </run>
    <run runId="1">
      <device>nexus5x</device>
      <path>bensonbingham.com/removepreload</path>
      <browser>chrome</browser>
      <runCount>2</runCount>
    </run>
    <run runId="38">
      <device>nexus5x</device>
      <path>africafreak.com/noremovepreload</path>
      <browser>chrome</browser>
      <runCount>4</runCount>
    </run>
    <run runId="246">
      <device>nexus5x</device>
      <path>scmp.com/noremovepreload</path>
      <browser>chrome</browser>
      <runCount>2</runCount>
    </run>
    <run runId="304">
      <device>nexus5x</device>
      <path>ict.moscow/removepreload</path>
      <browser>chrome</browser>
      <runCount>5</runCount>
    </run>
    <run runId="23">
      <device>nexus5x</device>
      <path>unilad.co.uk/removepreload</path>
      <browser>chrome</browser>
      <runCount>4</runCount>
    </run>
    <run runId="88">
      <device>nexus5x</device>
      <path>nbc.com/noremovepreload</path>
      <browser>chrome</browser>
      <runCount>4</runCount>
    </run>
    <run runId="93">
      <device>nexus5x</device>
      <path>agriwebb.com/removepreload</path>
      <browser>chrome</browser>
      <runCount>4</runCount>
    </run>
    <run runId="248">
      <device>nexus5x</device>
      <path>scmp.com/noremovepreload</path>
      <browser>chrome</browser>
      <runCount>4</runCount>
    </run>
    <run runId="28">
      <device>nexus5x</device>
      <path>unilad.co.uk/noremovepreload</path>
      <browser>chrome</browser>
      <runCount>4</runCount>
    </run>
    <run runId="43">
      <device>nexus5x</device>
      <path>traineracademy.org/removepreload</path>
      <browser>chrome</browser>
      <runCount>4</runCount>
    </run>
    <run runId="51">
      <device>nexus5x</device>
      <path>lisakristine.com/removepreload</path>
      <browser>chrome</browser>
      <runCount>2</runCount>
    </run>
    <run runId="45">
      <device>nexus5x</device>
      <path>traineracademy.org/noremovepreload</path>
      <browser>chrome</browser>
      <runCount>1</runCount>
    </run>
    <run runId="289">
      <device>nexus5x</device>
      <path>affirm.com/noremovepreload</path>
      <browser>chrome</browser>
      <runCount>5</runCount>
    </run>
    <run runId="267">
      <device>nexus5x</device>
      <path>jisr.net/noremovepreload</path>
      <browser>chrome</browser>
      <runCount>3</runCount>
    </run>
    <run runId="79">
      <device>nexus5x</device>
      <path>screenrant.com/noremovepreload</path>
      <browser>chrome</browser>
      <runCount>5</runCount>
    </run>
    <run runId="216">
      <device>nexus5x</device>
      <path>infobunny.com/noremovepreload</path>
      <browser>chrome</browser>
      <runCount>2</runCount>
    </run>
    <run runId="305">
      <device>nexus5x</device>
      <path>ict.moscow/noremovepreload</path>
      <browser>chrome</browser>
      <runCount>1</runCount>
    </run>
    <run runId="342">
      <device>nexus5x</device>
      <path>veronicatv.nl/removepreload</path>
      <browser>chrome</browser>
      <runCount>3</runCount>
    </run>
    <run runId="339">
      <device>nexus5x</device>
      <path>unclesamsmisguidedchildren.com/noremovepreload</path>
      <browser>chrome</browser>
      <runCount>5</runCount>
    </run>
    <run runId="166">
      <device>nexus5x</device>
      <path>animoto.com/noremovepreload</path>
      <browser>chrome</browser>
      <runCount>2</runCount>
    </run>
    <run runId="145">
      <device>nexus5x</device>
      <path>theodysseyonline.com/noremovepreload</path>
      <browser>chrome</browser>
      <runCount>1</runCount>
    </run>
    <run runId="154">
      <device>nexus5x</device>
      <path>dji.com/removepreload</path>
      <browser>chrome</browser>
      <runCount>5</runCount>
    </run>
    <run runId="353">
      <device>nexus5x</device>
      <path>sedanmed.ir/removepreload</path>
      <browser>chrome</browser>
      <runCount>4</runCount>
    </run>
    <run runId="323">
      <device>nexus5x</device>
      <path>sportbible.com/removepreload</path>
      <browser>chrome</browser>
      <runCount>4</runCount>
    </run>
    <run runId="369">
      <device>nexus5x</device>
      <path>newsbreak.com/noremovepreload</path>
      <browser>chrome</browser>
      <runCount>5</runCount>
    </run>
    <run runId="46">
      <device>nexus5x</device>
      <path>traineracademy.org/noremovepreload</path>
      <browser>chrome</browser>
      <runCount>2</runCount>
    </run>
    <run runId="68">
      <device>nexus5x</device>
      <path>home.pl/noremovepreload</path>
      <browser>chrome</browser>
      <runCount>4</runCount>
    </run>
    <run runId="295">
      <device>nexus5x</device>
      <path>noshift.com/noremovepreload</path>
      <browser>chrome</browser>
      <runCount>1</runCount>
    </run>
    <run runId="251">
      <device>nexus5x</device>
      <path>schmoozecom.com/removepreload</path>
      <browser>chrome</browser>
      <runCount>2</runCount>
    </run>
    <run runId="379">
      <device>nexus5x</device>
      <path>coindesk.com/noremovepreload</path>
      <browser>chrome</browser>
      <runCount>5</runCount>
    </run>
    <run runId="332">
      <device>nexus5x</device>
      <path>unclesamsmisguidedchildren.com/removepreload</path>
      <browser>chrome</browser>
      <runCount>3</runCount>
    </run>
    <run runId="99">
      <device>nexus5x</device>
      <path>agriwebb.com/noremovepreload</path>
      <browser>chrome</browser>
      <runCount>5</runCount>
    </run>
    <run runId="127">
      <device>nexus5x</device>
      <path>fastcodesign.com/noremovepreload</path>
      <browser>chrome</browser>
      <runCount>3</runCount>
    </run>
    <run runId="372">
      <device>nexus5x</device>
      <path>coindesk.com/removepreload</path>
      <browser>chrome</browser>
      <runCount>3</runCount>
    </run>
    <run runId="229">
      <device>nexus5x</device>
      <path>intercom.io/noremovepreload</path>
      <browser>chrome</browser>
      <runCount>5</runCount>
    </run>
    <run runId="255">
      <device>nexus5x</device>
      <path>schmoozecom.com/noremovepreload</path>
      <browser>chrome</browser>
      <runCount>1</runCount>
    </run>
    <run runId="117">
      <device>nexus5x</device>
      <path>cbc.ca/noremovepreload</path>
      <browser>chrome</browser>
      <runCount>3</runCount>
    </run>
    <run runId="360">
      <device>nexus5x</device>
      <path>newsbreak.com/removepreload</path>
      <browser>chrome</browser>
      <runCount>1</runCount>
    </run>
    <run runId="136">
      <device>nexus5x</device>
      <path>trustpilot.com/noremovepreload</path>
      <browser>chrome</browser>
      <runCount>2</runCount>
    </run>
    <run runId="311">
      <device>nexus5x</device>
      <path>ingenieriareal.com/removepreload</path>
      <browser>chrome</browser>
      <runCount>2</runCount>
    </run>
    <run runId="273">
      <device>nexus5x</device>
      <path>g-talent.net/removepreload</path>
      <browser>chrome</browser>
      <runCount>4</runCount>
    </run>
    <run runId="315">
      <device>nexus5x</device>
      <path>ingenieriareal.com/noremovepreload</path>
      <browser>chrome</browser>
      <runCount>1</runCount>
    </run>
    <run runId="239">
      <device>nexus5x</device>
      <path>beegru.com/noremovepreload</path>
      <browser>chrome</browser>
      <runCount>5</runCount>
    </run>
    <run runId="309">
      <device>nexus5x</device>
      <path>ict.moscow/noremovepreload</path>
      <browser>chrome</browser>
      <runCount>5</runCount>
    </run>
    <run runId="250">
      <device>nexus5x</device>
      <path>schmoozecom.com/removepreload</path>
      <browser>chrome</browser>
      <runCount>1</runCount>
    </run>
    <run runId="319">
      <device>nexus5x</device>
      <path>ingenieriareal.com/noremovepreload</path>
      <browser>chrome</browser>
      <runCount>5</runCount>
    </run>
    <run runId="365">
      <device>nexus5x</device>
      <path>newsbreak.com/noremovepreload</path>
      <browser>chrome</browser>
      <runCount>1</runCount>
    </run>
    <run runId="97">
      <device>nexus5x</device>
      <path>agriwebb.com/noremovepreload</path>
      <browser>chrome</browser>
      <runCount>3</runCount>
    </run>
    <run runId="113">
      <device>nexus5x</device>
      <path>cbc.ca/removepreload</path>
      <browser>chrome</browser>
      <runCount>4</runCount>
    </run>
    <run runId="11">
      <device>nexus5x</device>
      <path>squareinternet.co/removepreload</path>
      <browser>chrome</browser>
      <runCount>2</runCount>
    </run>
    <run runId="394">
      <device>nexus5x</device>
      <path>grantthornton.se/removepreload</path>
      <browser>chrome</browser>
      <runCount>5</runCount>
    </run>
    <run runId="85">
      <device>nexus5x</device>
      <path>nbc.com/noremovepreload</path>
      <browser>chrome</browser>
      <runCount>1</runCount>
    </run>
    <run runId="96">
      <device>nexus5x</device>
      <path>agriwebb.com/noremovepreload</path>
      <browser>chrome</browser>
      <runCount>2</runCount>
    </run>
    <run runId="380">
      <device>nexus5x</device>
      <path>parsely.com/removepreload</path>
      <browser>chrome</browser>
      <runCount>1</runCount>
    </run>
    <run runId="373">
      <device>nexus5x</device>
      <path>coindesk.com/removepreload</path>
      <browser>chrome</browser>
      <runCount>4</runCount>
    </run>
    <run runId="399">
      <device>nexus5x</device>
      <path>grantthornton.se/noremovepreload</path>
      <browser>chrome</browser>
      <runCount>5</runCount>
    </run>
  <run runId="385">
      <device>nexus5x</device>
      <path>parsely.com/noremovepreload</path>
      <browser>chrome</browser>
      <runCount>1</runCount>
    </run>
    <run runId="63">
      <device>nexus5x</device>
      <path>home.pl/removepreload</path>
      <browser>chrome</browser>
      <runCount>4</runCount>
    </run>
    <run runId="276">
      <device>nexus5x</device>
      <path>g-talent.net/noremovepreload</path>
      <browser>chrome</browser>
      <runCount>2</runCount>
    </run>
    <run runId="148">
      <device>nexus5x</device>
      <path>theodysseyonline.com/noremovepreload</path>
      <browser>chrome</browser>
      <runCount>4</runCount>
    </run>
    <run runId="65">
      <device>nexus5x</device>
      <path>home.pl/noremovepreload</path>
      <browser>chrome</browser>
      <runCount>1</runCount>
    </run>
    <run runId="285">
      <device>nexus5x</device>
      <path>affirm.com/noremovepreload</path>
      <browser>chrome</browser>
      <runCount>1</runCount>
    </run>
    <run runId="312">
      <device>nexus5x</device>
      <path>ingenieriareal.com/removepreload</path>
      <browser>chrome</browser>
      <runCount>3</runCount>
    </run>
    <run runId="254">
      <device>nexus5x</device>
      <path>schmoozecom.com/removepreload</path>
      <browser>chrome</browser>
      <runCount>5</runCount>
    </run>
    <run runId="249">
      <device>nexus5x</device>
      <path>scmp.com/noremovepreload</path>
      <browser>chrome</browser>
      <runCount>5</runCount>
    </run>
    <run runId="69">
      <device>nexus5x</device>
      <path>home.pl/noremovepreload</path>
      <browser>chrome</browser>
      <runCount>5</runCount>
    </run>
    <run runId="164">
      <device>nexus5x</device>
      <path>animoto.com/removepreload</path>
      <browser>chrome</browser>
      <runCount>5</runCount>
    </run>
    <run runId="257">
      <device>nexus5x</device>
      <path>schmoozecom.com/noremovepreload</path>
      <browser>chrome</browser>
      <runCount>3</runCount>
    </run>
    <run runId="165">
      <device>nexus5x</device>
      <path>animoto.com/noremovepreload</path>
      <browser>chrome</browser>
      <runCount>1</runCount>
    </run>
    <run runId="301">
      <device>nexus5x</device>
      <path>ict.moscow/removepreload</path>
      <browser>chrome</browser>
      <runCount>2</runCount>
    </run>
    <run runId="124">
      <device>nexus5x</device>
      <path>fastcodesign.com/removepreload</path>
      <browser>chrome</browser>
      <runCount>5</runCount>
    </run>
    <run runId="4">
      <device>nexus5x</device>
      <path>bensonbingham.com/removepreload</path>
      <browser>chrome</browser>
      <runCount>5</runCount>
    </run>
    <run runId="178">
      <device>nexus5x</device>
      <path>blistex.com/noremovepreload</path>
      <browser>chrome</browser>
      <runCount>4</runCount>
    </run>
    <run runId="36">
      <device>nexus5x</device>
      <path>africafreak.com/noremovepreload</path>
      <browser>chrome</browser>
      <runCount>2</runCount>
    </run>
    <run runId="62">
      <device>nexus5x</device>
      <path>home.pl/removepreload</path>
      <browser>chrome</browser>
      <runCount>3</runCount>
    </run>
    <run runId="211">
      <device>nexus5x</device>
      <path>infobunny.com/removepreload</path>
      <browser>chrome</browser>
      <runCount>2</runCount>
    </run>
    <run runId="181">
      <device>nexus5x</device>
      <path>fitchratings.ru/removepreload</path>
      <browser>chrome</browser>
      <runCount>2</runCount>
    </run>
    <run runId="155">
      <device>nexus5x</device>
      <path>dji.com/noremovepreload</path>
      <browser>chrome</browser>
      <runCount>1</runCount>
    </run>
    <run runId="129">
      <device>nexus5x</device>
      <path>fastcodesign.com/noremovepreload</path>
      <browser>chrome</browser>
      <runCount>5</runCount>
    </run>
    <run runId="102">
      <device>nexus5x</device>
      <path>musicgreatness.com/removepreload</path>
      <browser>chrome</browser>
      <runCount>3</runCount>
    </run>
    <run runId="10">
      <device>nexus5x</device>
      <path>squareinternet.co/removepreload</path>
      <browser>chrome</browser>
      <runCount>1</runCount>
    </run>
    <run runId="279">
      <device>nexus5x</device>
      <path>g-talent.net/noremovepreload</path>
      <browser>chrome</browser>
      <runCount>5</runCount>
    </run>
    <run runId="64">
      <device>nexus5x</device>
      <path>home.pl/removepreload</path>
      <browser>chrome</browser>
      <runCount>5</runCount>
    </run>
    <run runId="243">
      <device>nexus5x</device>
      <path>scmp.com/removepreload</path>
      <browser>chrome</browser>
      <runCount>4</runCount>
    </run>
    <run runId="318">
      <device>nexus5x</device>
      <path>ingenieriareal.com/noremovepreload</path>
      <browser>chrome</browser>
      <runCount>4</runCount>
    </run>
    <run runId="157">
      <device>nexus5x</device>
      <path>dji.com/noremovepreload</path>
      <browser>chrome</browser>
      <runCount>3</runCount>
    </run>
    <run runId="92">
      <device>nexus5x</device>
      <path>agriwebb.com/removepreload</path>
      <browser>chrome</browser>
      <runCount>3</runCount>
    </run>
    <run runId="341">
      <device>nexus5x</device>
      <path>veronicatv.nl/removepreload</path>
      <browser>chrome</browser>
      <runCount>2</runCount>
    </run>
    <run runId="344">
      <device>nexus5x</device>
      <path>veronicatv.nl/removepreload</path>
      <browser>chrome</browser>
      <runCount>5</runCount>
    </run>
    <run runId="72">
      <device>nexus5x</device>
      <path>screenrant.com/removepreload</path>
      <browser>chrome</browser>
      <runCount>3</runCount>
    </run>
    <run runId="50">
      <device>nexus5x</device>
      <path>lisakristine.com/removepreload</path>
      <browser>chrome</browser>
      <runCount>1</runCount>
    </run>
    <run runId="159">
      <device>nexus5x</device>
      <path>dji.com/noremovepreload</path>
      <browser>chrome</browser>
      <runCount>5</runCount>
    </run>
    <run runId="150">
      <device>nexus5x</device>
      <path>dji.com/removepreload</path>
      <browser>chrome</browser>
      <runCount>1</runCount>
    </run>
    <run runId="317">
      <device>nexus5x</device>
      <path>ingenieriareal.com/noremovepreload</path>
      <browser>chrome</browser>
      <runCount>3</runCount>
    </run>
    <run runId="378">
      <device>nexus5x</device>
      <path>coindesk.com/noremovepreload</path>
      <browser>chrome</browser>
      <runCount>4</runCount>
    </run>
    <run runId="81">
      <device>nexus5x</device>
      <path>nbc.com/removepreload</path>
      <browser>chrome</browser>
      <runCount>2</runCount>
    </run>
    <run runId="388">
      <device>nexus5x</device>
      <path>parsely.com/noremovepreload</path>
      <browser>chrome</browser>
      <runCount>4</runCount>
    </run>
    <run runId="203">
      <device>nexus5x</device>
      <path>ladbible.com/removepreload</path>
      <browser>chrome</browser>
      <runCount>4</runCount>
    </run>
    <run runId="182">
      <device>nexus5x</device>
      <path>fitchratings.ru/removepreload</path>
      <browser>chrome</browser>
      <runCount>3</runCount>
    </run>
    <run runId="244">
      <device>nexus5x</device>
      <path>scmp.com/removepreload</path>
      <browser>chrome</browser>
      <runCount>5</runCount>
    </run>
    <run runId="132">
      <device>nexus5x</device>
      <path>trustpilot.com/removepreload</path>
      <browser>chrome</browser>
      <runCount>3</runCount>
    </run>
    <run runId="308">
      <device>nexus5x</device>
      <path>ict.moscow/noremovepreload</path>
      <browser>chrome</browser>
      <runCount>4</runCount>
    </run>
    <run runId="27">
      <device>nexus5x</device>
      <path>unilad.co.uk/noremovepreload</path>
      <browser>chrome</browser>
      <runCount>3</runCount>
    </run>
    <run runId="205">
      <device>nexus5x</device>
      <path>ladbible.com/noremovepreload</path>
      <browser>chrome</browser>
      <runCount>1</runCount>
    </run>
    <run runId="333">
      <device>nexus5x</device>
      <path>unclesamsmisguidedchildren.com/removepreload</path>
      <browser>chrome</browser>
      <runCount>4</runCount>
    </run>
    <run runId="238">
      <device>nexus5x</device>
      <path>beegru.com/noremovepreload</path>
      <browser>chrome</browser>
      <runCount>4</runCount>
    </run>
    <run runId="174">
      <device>nexus5x</device>
      <path>blistex.com/removepreload</path>
      <browser>chrome</browser>
      <runCount>5</runCount>
    </run>
    <run runId="142">
      <device>nexus5x</device>
      <path>theodysseyonline.com/removepreload</path>
      <browser>chrome</browser>
      <runCount>3</runCount>
    </run>
    <run runId="290">
      <device>nexus5x</device>
      <path>noshift.com/removepreload</path>
      <browser>chrome</browser>
      <runCount>1</runCount>
    </run>
    <run runId="197">
      <device>nexus5x</device>
      <path>berlinomagazine.com/noremovepreload</path>
      <browser>chrome</browser>
      <runCount>3</runCount>
    </run>
    <run runId="387">
      <device>nexus5x</device>
      <path>parsely.com/noremovepreload</path>
      <browser>chrome</browser>
      <runCount>3</runCount>
    </run>
    <run runId="143">
      <device>nexus5x</device>
      <path>theodysseyonline.com/removepreload</path>
      <browser>chrome</browser>
      <runCount>4</runCount>
    </run>
    <run runId="322">
      <device>nexus5x</device>
      <path>sportbible.com/removepreload</path>
      <browser>chrome</browser>
      <runCount>3</runCount>
    </run>
    <run runId="83">
      <device>nexus5x</device>
      <path>nbc.com/removepreload</path>
      <browser>chrome</browser>
      <runCount>4</runCount>
    </run>
    <run runId="179">
      <device>nexus5x</device>
      <path>blistex.com/noremovepreload</path>
      <browser>chrome</browser>
      <runCount>5</runCount>
    </run>
    <run runId="153">
      <device>nexus5x</device>
      <path>dji.com/removepreload</path>
      <browser>chrome</browser>
      <runCount>4</runCount>
    </run>
    <run runId="300">
      <device>nexus5x</device>
      <path>ict.moscow/removepreload</path>
      <browser>chrome</browser>
      <runCount>1</runCount>
    </run>
    <run runId="87">
      <device>nexus5x</device>
      <path>nbc.com/noremovepreload</path>
      <browser>chrome</browser>
      <runCount>3</runCount>
    </run>
    <run runId="272">
      <device>nexus5x</device>
      <path>g-talent.net/removepreload</path>
      <browser>chrome</browser>
      <runCount>3</runCount>
    </run>
    <run runId="121">
      <device>nexus5x</device>
      <path>fastcodesign.com/removepreload</path>
      <browser>chrome</browser>
      <runCount>2</runCount>
    </run>
    <run runId="134">
      <device>nexus5x</device>
      <path>trustpilot.com/removepreload</path>
      <browser>chrome</browser>
      <runCount>5</runCount>
    </run>
    <run runId="363">
      <device>nexus5x</device>
      <path>newsbreak.com/removepreload</path>
      <browser>chrome</browser>
      <runCount>4</runCount>
    </run>
    <run runId="223">
      <device>nexus5x</device>
      <path>intercom.io/removepreload</path>
      <browser>chrome</browser>
      <runCount>4</runCount>
    </run>
    <run runId="262">
      <device>nexus5x</device>
      <path>jisr.net/removepreload</path>
      <browser>chrome</browser>
      <runCount>3</runCount>
    </run>
    <run runId="183">
      <device>nexus5x</device>
      <path>fitchratings.ru/removepreload</path>
      <browser>chrome</browser>
      <runCount>4</runCount>
    </run>
    <run runId="118">
      <device>nexus5x</device>
      <path>cbc.ca/noremovepreload</path>
      <browser>chrome</browser>
      <runCount>4</runCount>
    </run>
    <run runId="269">
      <device>nexus5x</device>
      <path>jisr.net/noremovepreload</path>
      <browser>chrome</browser>
      <runCount>5</runCount>
    </run>
    <run runId="41">
      <device>nexus5x</device>
      <path>traineracademy.org/removepreload</path>
      <browser>chrome</browser>
      <runCount>2</runCount>
    </run>
    <run runId="389">
      <device>nexus5x</device>
      <path>parsely.com/noremovepreload</path>
      <browser>chrome</browser>
      <runCount>5</runCount>
    </run>
    <run runId="393">
      <device>nexus5x</device>
      <path>grantthornton.se/removepreload</path>
      <browser>chrome</browser>
      <runCount>4</runCount>
    </run>
    <run runId="20">
      <device>nexus5x</device>
      <path>unilad.co.uk/removepreload</path>
      <browser>chrome</browser>
      <runCount>1</runCount>
    </run>
    <run runId="175">
      <device>nexus5x</device>
      <path>blistex.com/noremovepreload</path>
      <browser>chrome</browser>
      <runCount>1</runCount>
    </run>
    <run runId="208">
      <device>nexus5x</device>
      <path>ladbible.com/noremovepreload</path>
      <browser>chrome</browser>
      <runCount>4</runCount>
    </run>
    <run runId="44">
      <device>nexus5x</device>
      <path>traineracademy.org/removepreload</path>
      <browser>chrome</browser>
      <runCount>5</runCount>
    </run>
    <run runId="169">
      <device>nexus5x</device>
      <path>animoto.com/noremovepreload</path>
      <browser>chrome</browser>
      <runCount>5</runCount>
    </run>
    <run runId="55">
      <device>nexus5x</device>
      <path>lisakristine.com/noremovepreload</path>
      <browser>chrome</browser>
      <runCount>1</runCount>
    </run>
    <run runId="123">
      <device>nexus5x</device>
      <path>fastcodesign.com/removepreload</path>
      <browser>chrome</browser>
      <runCount>4</runCount>
    </run>
    <run runId="306">
      <device>nexus5x</device>
      <path>ict.moscow/noremovepreload</path>
      <browser>chrome</browser>
      <runCount>2</runCount>
    </run>
    <run runId="256">
      <device>nexus5x</device>
      <path>schmoozecom.com/noremovepreload</path>
      <browser>chrome</browser>
      <runCount>2</runCount>
    </run>
    <run runId="314">
      <device>nexus5x</device>
      <path>ingenieriareal.com/removepreload</path>
      <browser>chrome</browser>
      <runCount>5</runCount>
    </run>
    <run runId="5">
      <device>nexus5x</device>
      <path>bensonbingham.com/noremovepreload</path>
      <browser>chrome</browser>
      <runCount>1</runCount>
    </run>
    <run runId="116">
      <device>nexus5x</device>
      <path>cbc.ca/noremovepreload</path>
      <browser>chrome</browser>
      <runCount>2</runCount>
    </run>
    <run runId="275">
      <device>nexus5x</device>
      <path>g-talent.net/noremovepreload</path>
      <browser>chrome</browser>
      <runCount>1</runCount>
    </run>
    <run runId="9">
      <device>nexus5x</device>
      <path>bensonbingham.com/noremovepreload</path>
      <browser>chrome</browser>
      <runCount>5</runCount>
    </run>
    <run runId="78">
      <device>nexus5x</device>
      <path>screenrant.com/noremovepreload</path>
      <browser>chrome</browser>
      <runCount>4</runCount>
    </run>
    <run runId="298">
      <device>nexus5x</device>
      <path>noshift.com/noremovepreload</path>
      <browser>chrome</browser>
      <runCount>4</runCount>
    </run>
    <run runId="236">
      <device>nexus5x</device>
      <path>beegru.com/noremovepreload</path>
      <browser>chrome</browser>
      <runCount>2</runCount>
    </run>
    </runsDone>
</experiment>
